{"id":103,"name":"Đặng Tiểu Bình","aliases":["Đặng Tiểu Bình 邓小平","Đặng Tiểu Bình"],"realName":"tên khai sinh là Đặng Tiên Thánh","born":"22 tháng 8, 1904","died":"19 tháng 2, 1997 (92 tuổi)","overview":"Chủ nhiệm Ủy ban Cố vấn Trung ương Đảng Cộng sản Trung Quốc","workTime":"13 tháng 9 năm 1982 – 2 tháng 11 năm 1987 5 năm, 50 ngày","era":{"key":"Chưa rõ","value":null},"father":{"key":"Chưa rõ","value":null},"mother":{"key":"Chưa rõ","value":null},"precededBy":{"key":"Chức vụ được thành lập","value":null},"succeededBy":{"key":"Trần Vân","value":null}}