{"id":1116,"name":"Trần Hữu Lượng","aliases":["Trần Hữu Lượng (陳友諒)","Đại Nghĩa 1360 Đại Định 1361-1363","không","Cao Tổ (高祖)","Trần Hữu Lượng"],"realName":"Trần Hữu Lượng","born":"1320","died":"3 tháng 10, 1363 Hồ Bà Dương","overview":"là một thủ lĩnh quân phiệt thời \"Nguyên mạt Minh sơ\" trong lịch sử Trung Quốc, là người Miện Dương, Hồ Bắc ","workTime":"1360 - 1363","era":{"key":"Đại Hán (大漢)","value":null},"father":{"key":"Trần Phổ Tài","value":500},"mother":{"key":"?","value":500},"precededBy":{"key":"Không","value":500},"succeededBy":{"key":"Trần Lý","value":500}}