{"id":172,"name":"Hồ Hán Thương","aliases":["Thiệu Thành (1401 - 1402) Khai Đại (1403 - 1407)"],"overview":"là hoàng đế thứ hai và cũng là cuối cùng của nhà Hồ, cai trị nước Đại Ngu từ năm 1401 đến 1407","realName":"Hồ Hán Thương","born":"?","died":"1407","workTime":"1401 - 1407","era":{"key":"Nhà Hồ","value":16},"father":{"key":"Hồ Quý Ly","value":178},"mother":{"key":"Công chúa Huy Ninh","value":null},"precededBy":{"key":"Hồ Quý Ly","value":178},"succeededBy":{"key":"Triều đại sụp đổ Giản Định Đế (Nhà Hậu Trần)","value":null}}