{"id":385,"name":"Kiến vương Tân 建王鑌","aliases":["Phối Thiên Dụ Thánh Ôn Lương Quang Minh Văn Triết Khoan Hoằng Chương Tín Tuy Hưu Mục Hiếu Kiến hoàng đế (配天裕聖溫良光明文哲寬弘彰信綏休睦孝建皇帝)"],"realName":"Lê Tân (黎鑌)","born":"19 tháng 8, 1466 Đông Kinh","died":"6 tháng 11, 1502 (36 tuổi) Đông Kinh","overview":"là một tông thất nhà Lê sơ trong lịch sử Việt Nam","workTime":"Chưa rõ","era":{"key":"Nhà Hậu Lê – giai đoạn Lê sơ","value":19},"father":{"key":"Lê Thánh Tông","value":393},"mother":{"key":"Nhu Huy hoàng hậu","value":null},"precededBy":{"key":"Chưa rõ","value":null},"succeededBy":{"key":"Chưa rõ","value":null},"allPossibleNames":["Phối Thiên Dụ Thánh Ôn Lương Quang Minh Văn Triết Khoan Hoằng Chương Tín Tuy Hưu Mục Hiếu Kiến hoàng đế (配天裕聖溫良光明文哲寬弘彰信綏休睦孝建皇帝)","Kiến vương Tân 建王鑌"]}