{"id":452,"name":"Lý Nam Đế 李南帝","aliases":["Thiên Đức (天徳)","Nam Đế (南帝)"],"overview":"là vị vua đầu tiên của nhà Tiền Lý và nước Vạn Xuân","realName":"Lý Bí hoặc Lý Bôn (李賁)","born":"17 tháng 10, 503","died":"13 tháng 4, 548 (44 tuổi) Việt Nam","workTime":"544 – 548","era":{"key":"Nhà Tiền Lý","value":5},"father":{"key":"Lý Cạnh hay Lý Toản","value":null},"mother":{"key":"Lê Thị Oánh","value":null},"precededBy":{"key":"Chưa rõ","value":713},"succeededBy":{"key":"Triệu Việt Vương","value":1250}}