{"id":692,"name":"Tiên Vương 僊王","aliases":["Triệu Cơ Thùy Thống Khâm Minh Cung Ý Cần Nghĩa Đạt Lý hiển Ứng Chiêu Hựu Diệu Linh Gia Dụ Hoàng đế (肇基垂統欽明恭懿謹義達理顯應昭祐耀靈嘉裕皇帝) Ngắn: Gia Dụ hoàng đế (嘉裕皇帝"],"overview":"Chúa Nguyễn","realName":"Nguyễn Hoàng (阮潢)","born":"28 tháng 8, 1525 Thanh Hóa, Đại Việt","died":"20 tháng 7, 1613 (87 tuổi) Đàng Trong, Đại Việt","workTime":"1558 - 1613","era":{"key":"Họ Nguyễn","value":null},"father":{"key":"Nguyễn Kim","value":null},"mother":{"key":"Nguyễn Thị Mai","value":834},"precededBy":{"key":"Sáng lập","value":null},"succeededBy":{"key":"Nguyễn Phúc Nguyên","value":null}}