{"id":715,"name":"Nguyễn Huy Hiệu","aliases":["Nguyễn Huy Hiệu","Nguyễn Huy Hiệu"],"realName":"Nguyễn Huy Hiệu","born":"17 tháng 7, 1947 (73 tuổi) Xã Hải Long, huyện Hải Hậu, tỉnh Nam Định, Việt Nam Dân chủ Cộng hòa","died":"Chưa rõ","overview":"Thứ trưởng Bộ Quốc phòng Việt Nam","workTime":"tháng 11 năm 1998 – 2011","era":{"key":"Chưa rõ","value":null},"father":{"key":"Chưa rõ","value":null},"mother":{"key":"Chưa rõ","value":null},"precededBy":{"key":"Nguyễn Kiệm","value":731},"succeededBy":{"key":"Đỗ Trung Dương","value":null}}