{"id":1,"name":"Chiến khu Tân Trào","aliases":[],"overview":"là khu di tích lịch sử của cách mạng Việt Nam thời kỳ Cách mạng tháng Tám","location":"thuộc huyện Sơn Dương, tỉnh Tuyên Quang, cách Thành phố Tuyên Quang khoảng 41 km, cách Hà Nội khoảng 150 km, với diện tích khoảng 6","constructionDate":"xây dựng vào năm 1923 theo kiểu nhà sàn, cột gỗ, ba gian hai chái, mái lợp lá cọ, sàn lát ván, để đáp ứng nhu cầu tín ngưỡng và là nơi hội họp, sinh hoạt văn hoá của dân làng","founder":"Chưa rõ","relatedFestivalId":{"Chưa rõ":null},"relatedFiguresId":{"Hồ Chí Minh":170,"Võ Nguyên Giáp":1328}}