{"id":741,"name":"Đền Đông Hội","aliases":[],"location":"Ninh An - Hoa Lư","constructionDate":"Chưa rõ","founder":"Chưa rõ","relatedFestivalId":{"Theo Thánh phả để lại vào những năm tý, ngọ, mão, dậu, nhân dân trong xã long trọng tổ chức lễ hội chính khóa để tưởng nhớ công đức của ba vị tướng trên đã có công hộ quốc an dân.":null},"overview":"là đền thờ cổ nằm ở thôn Đông Hội, xã Ninh An, huyện Hoa Lư, tỉnh Ninh Bình","note":"Đền Đông Hội là một trong các di tích có sớm nhất Ninh Bình, từ thời Hai Bà Trưng gọi là Chùa Thanh Xuân. Đền thờ ba anh em, là Đống Bụt, Diệu Vũ và Ngọc nữ Trần Hoa.","category":"Chưa rõ","approvedYear":"Chưa rõ","relatedFiguresId":{"Hai Bà Trưng":165}}